vllm_flash_attn_2_cuda.cpython-310-x86_64-linux-gnu.so
vllm_flash_attn/__init__.py
vllm_flash_attn/flash_attn_interface.py
vllm_flash_attn-2.6.2.dist-info/AUTHORS
vllm_flash_attn-2.6.2.dist-info/LICENSE
vllm_flash_attn-2.6.2.dist-info/METADATA
vllm_flash_attn-2.6.2.dist-info/WHEEL
vllm_flash_attn-2.6.2.dist-info/top_level.txt
vllm_flash_attn-2.6.2.dist-info/RECORD
